wxautocompletectrl.py
wxautocompletectrl-1.0.0.dist-info/METADATA
wxautocompletectrl-1.0.0.dist-info/RECORD
wxautocompletectrl-1.0.0.dist-info/WHEEL
wxautocompletectrl-1.0.0.dist-info/top_level.txt
wxautocompletectrl-1.0.0.dist-info/zip-safe
