Metadata-Version: 2.1
Name: wxautocompletectrl
Version: 1.0.0
Summary: AutocompleteTextCtrl for wxPython
Home-page: https://bitbucket.org/raz/wxautocompletectrl
Author: Toni Ruža
Author-email: toni.ruza@gmail.com
License: BSD-2-Clause
Keywords: wxpython autocomplete
Platform: any
Classifier: Development Status :: 5 - Production/Stable
Classifier: License :: OSI Approved :: BSD License
Classifier: Intended Audience :: Developers
Classifier: Programming Language :: Python :: 3.4
Classifier: Programming Language :: Python :: 3.5
Classifier: Programming Language :: Python :: 3.6
Classifier: Programming Language :: Python :: Implementation :: CPython
Classifier: Operating System :: OS Independent
Requires-Python: >=3.4
Requires-Dist: wxpython
